scs_architecture_handlers/__init__.py
scs_architecture_handlers/base_handler.py
scs_architecture_handlers/f5tts_handler.py
scs_architecture_handlers/face_recognition_handler.py
scs_architecture_handlers/gesture_generation_handler.py
scs_architecture_handlers/gesture_generation_helper.py
scs_architecture_handlers/llm_agent_handler.py
scs_architecture_handlers/maverick_agent_handler.py
scs_architecture_handlers/ollama_handler.py
scs_architecture_handlers/stt_handler.py
scs_architecture_handlers/usage_examples/__init__.py
scs_architecture_handlers/usage_examples/f5tts_handler_demo.py
scs_architecture_handlers/usage_examples/face_recogintion_demo.py
scs_architecture_handlers-0.2.2.dist-info/METADATA
scs_architecture_handlers-0.2.2.dist-info/WHEEL
scs_architecture_handlers-0.2.2.dist-info/top_level.txt
scs_architecture_handlers-0.2.2.dist-info/RECORD
