Metadata-Version: 2.4
Name: scs-architecture-handlers
Version: 0.2.2
Summary: ArchitectureHandlers for all parts of the Maverick Architecture
Author: SCS
License: MIT
Project-URL: Homepage, https://gitlab.ub.uni-bielefeld.de/scs/enrico/modules/architecture-handlers
Requires-Python: >=3.10
Requires-Dist: numpy>=1.24
Requires-Dist: requests>=2.31
Requires-Dist: Pillow>=9.5
Requires-Dist: realtimestt-multiclient>=0.1.5
Requires-Dist: ollama
Requires-Dist: opencv-python
Requires-Dist: pytest
